archerdfu/core.py
archerdfu.core-1.0.2.dist-info/LICENSE
archerdfu.core-1.0.2.dist-info/METADATA
archerdfu.core-1.0.2.dist-info/WHEEL
archerdfu.core-1.0.2.dist-info/top_level.txt
archerdfu.core-1.0.2.dist-info/RECORD
