Metadata-Version: 2.1
Name: archerdfu.core
Version: 1.0.2
Summary: PyDfuUtil binds for archerdfu library
Author: o-murphy
License: GNU GENERAL PUBLIC LICENSE
Project-URL: Homepage, https://github.com/archerdfu/archerdfu.core
Project-URL: Bug Reports, https://github.com/archerdfu/archerdfu.core/issues
Project-URL: Source, https://github.com/archerdfu/archerdfu.core
Keywords: ARCHER,archerdfu,pydfuutil,dfuutil
Classifier: Intended Audience :: Developers
Classifier: Natural Language :: English
Classifier: Programming Language :: Python
Classifier: Topic :: Software Development :: Libraries :: Python Modules
Classifier: Programming Language :: Python :: 3
Classifier: Programming Language :: Python :: 3 :: Only
Classifier: Programming Language :: Python :: 3.9
Classifier: Programming Language :: Python :: 3.10
Classifier: Programming Language :: Python :: 3.11
Classifier: Programming Language :: Python :: 3.12
Classifier: Programming Language :: Python :: Implementation :: CPython
Requires-Python: >=3.9
License-File: LICENSE
Requires-Dist: pydfuutil >=0.0.2b0
Requires-Dist: rich >=13.7.0
